LICENSE
setup.py
nnio/__init__.py
nnio/edgetpu.py
nnio/model.py
nnio/onnx.py
nnio/openvino.py
nnio/output.py
nnio/preprocessing.py
nnio/pytorch.py
nnio/utils.py
nnio/wrapper.py
nnio.egg-info/PKG-INFO
nnio.egg-info/SOURCES.txt
nnio.egg-info/dependency_links.txt
nnio.egg-info/requires.txt
nnio.egg-info/top_level.txt
nnio/zoo/__init__.py
nnio/zoo/edgetpu/__init__.py
nnio/zoo/edgetpu/classification.py
nnio/zoo/edgetpu/detection.py
nnio/zoo/edgetpu/reid.py
nnio/zoo/edgetpu/segmentation.py
nnio/zoo/onnx/__init__.py
nnio/zoo/onnx/classification.py
nnio/zoo/onnx/detection.py
nnio/zoo/onnx/reid.py
nnio/zoo/openvino/__init__.py
nnio/zoo/openvino/detection.py
nnio/zoo/openvino/reid.py