Metadata-Version: 2.1
Name: nnio
Version: 0.3.1.2
Summary: Neural network inference on accelerators simplified
Home-page: https://github.com/FastSense/nnio
Author: Ruslan Baynazarov
Author-email: ruslan.baynazarov@fastsense.tech
License: MIT
Platform: UNKNOWN
License-File: LICENSE
